pb2/__init__.py
pb2/pb2.cp311-win_amd64.pyd
pb2/pb2.cp312-win_amd64.pyd
pb2/pb2.cp313-win_amd64.pyd
pb2-0.6.11.dist-info/licenses/LICENSE
pb2-0.6.11.dist-info/METADATA
pb2-0.6.11.dist-info/WHEEL
pb2-0.6.11.dist-info/top_level.txt
pb2-0.6.11.dist-info/RECORD
