Metadata-Version: 2.4
Name: pb2
Version: 0.6.11
Summary: PB2
Author-email: louis <pybooster2@gmail.com>
Requires-Python: >=3.11
License-File: LICENSE
Requires-Dist: requests>=2.1
Requires-Dist: numpy>=2.0
Requires-Dist: Cython>=3.0
Requires-Dist: setuptools>70.0
Dynamic: license-file
